pyiptp/__init__.pxd
pyiptp/__init__.py
pyiptp/basicfunc.c
pyiptp/basicfunc.cp37-win_amd64.pyd
pyiptp/basicfunc.pxd
pyiptp/basicfunc.pyx
pyiptp/cython_ubsplclib.c
pyiptp/cython_ubsplclib.cp37-win_amd64.pyd
pyiptp/cython_ubsplclib.pxd
pyiptp/cython_ubsplclib.pyx
pyiptp/defdatastruct.c
pyiptp/defdatastruct.cp37-win_amd64.pyd
pyiptp/defdatastruct.pxd
pyiptp/defdatastruct.pyx
pyiptp/factoryfunc.c
pyiptp/factoryfunc.cp37-win_amd64.pyd
pyiptp/factoryfunc.pxd
pyiptp/factoryfunc.pyx
pyiptp/ubsplclib.c
pyiptp/ubsplclib.h
pyiptp/utils.pxi
pyiptp-0.1.0.dist-info/LICENSE
pyiptp-0.1.0.dist-info/METADATA
pyiptp-0.1.0.dist-info/WHEEL
pyiptp-0.1.0.dist-info/top_level.txt
pyiptp-0.1.0.dist-info/RECORD
