Metadata-Version: 2.1
Name: pyiptp
Version: 0.1.0
Summary: Iso-Parametric Trajectory Planning python toolkit
Home-page: https://github.com/projectcamomile/pyiptp
Author: Marco Riboli
Author-email: marco.riboli@unipr.it
License: BSD-3-Clause
Platform: any
Classifier: Development Status :: 1 - Planning
Classifier: Environment :: Console
Classifier: Intended Audience :: Science/Research
Classifier: License :: OSI Approved :: BSD License
Classifier: Operating System :: OS Independent
Classifier: Programming Language :: C
Classifier: Programming Language :: Cython
Classifier: Programming Language :: Python :: 3
Classifier: Topic :: Scientific/Engineering
Requires-Python: >=3.6
License-File: LICENSE
Requires-Dist: numpy (>=1.19.2)
Requires-Dist: scipy (>=1.5.2)
Requires-Dist: lxml (>=4.6.3)
